{
    "key": "group_58c7cdc28caf6",
    "title": "[Post Format] Link",
    "fields": [
        {
            "key": "field_58c7cde415e47",
            "label": "URL",
            "name": "link_format_post_options",
            "type": "url",
            "value": null,
            "instructions": "",
            "required": 0,
            "conditional_logic": 0,
            "wrapper": {
                "width": "",
                "class": "",
                "id": ""
            },
            "default_value": "",
            "placeholder": ""
        }
    ],
    "location": [
        [
            {
                "param": "post_format",
                "operator": "==",
                "value": "link"
            },
            {
                "param": "post_type",
                "operator": "==",
                "value": "post"
            }
        ]
    ],
    "menu_order": 0,
    "position": "normal",
    "style": "default",
    "label_placement": "top",
    "instruction_placement": "label",
    "hide_on_screen": "",
    "active": 1,
    "description": "",
    "modified": 1509896320
}